{
  "timestamp": "2026-07-02T11:12:54",
  "total_scenarios": 10,
  "passed": 10,
  "pass_rate": "100%",
  "scenarios": [
    {
      "id": "S1",
      "name": "同义词联想",
      "query": "妈妈多大了",
      "passed": true,
      "top1_hit": true,
      "top3_hit": true,
      "top3_scores": [
        5.26,
        0.5,
        0.5
      ],
      "top3_texts": [
        "妈妈今年55岁，已经退休了。",
        "我今年30岁，在一家互联网公司工作。",
        "爸爸今年58岁，还在上班。"
      ],
      "analysis": "✅ 最佳匹配在第1位"
    },
    {
      "id": "S2",
      "name": "近义词联想",
      "query": "HHKB好用吗",
      "passed": true,
      "top1_hit": true,
      "top3_hit": true,
      "top3_scores": [
        1.71,
        0.5,
        0.5
      ],
      "top3_texts": [
        "我最喜欢机械键盘，打字手感特别好。",
        "鼠标我用的是罗技的无线鼠标。",
        "显示器是戴尔的27寸4K屏。"
      ],
      "analysis": "✅ 最佳匹配在第1位"
    },
    {
      "id": "S3",
      "name": "跨实体推理",
      "query": "张三同事的老婆",
      "passed": true,
      "top1_hit": true,
      "top3_hit": true,
      "top3_scores": [
        6.67,
        0.5,
        0.5
      ],
      "top3_texts": [
        "李丽是我的大学同学，张三是我的前同事。",
        "王芳在北京协和医院工作。",
        "李丽是家庭主妇，没有上班。"
      ],
      "analysis": "✅ 最佳匹配在第1位"
    },
    {
      "id": "S4",
      "name": "否定查询/跨人物",
      "query": "李四买特斯拉了吗",
      "passed": true,
      "top1_hit": false,
      "top3_hit": true,
      "top3_scores": [
        3.77,
        1.4600000000000004,
        0.5
      ],
      "top3_texts": [
        "特斯拉最近降价了。",
        "张三上个月买了一辆特斯拉。",
        "李四最近在考虑买电动车。"
      ],
      "analysis": "⚠ 最佳匹配在第3位（非首位）"
    },
    {
      "id": "S5",
      "name": "时间推理",
      "query": "去年发生了什么",
      "passed": true,
      "top1_hit": false,
      "top3_hit": true,
      "top3_scores": [
        0.55,
        0.55,
        0.5
      ],
      "top3_texts": [
        "2024年爸爸换了个新工作。",
        "2025年妈妈退休了，回家种花。",
        "我2023年大学毕业。"
      ],
      "analysis": "⚠ 最佳匹配在第2位（非首位）"
    },
    {
      "id": "S6",
      "name": "隐含推理（因果）",
      "query": "谁送我键盘的原因",
      "passed": true,
      "top1_hit": true,
      "top3_hit": true,
      "top3_scores": [
        2.96,
        0.6,
        0.15000000000000002
      ],
      "top3_texts": [
        "张三送我一把HHKB键盘，因为是生日礼物。",
        "李四也送了我一本书，挺好看的。",
        "我每年生日都会给自己买个礼物。"
      ],
      "analysis": "✅ 最佳匹配在第1位"
    },
    {
      "id": "S7",
      "name": "语义相似（体重）",
      "query": "我最近胖了",
      "passed": true,
      "top1_hit": false,
      "top3_hit": true,
      "top3_scores": [
        2.1599999999999997,
        0.2,
        0.2
      ],
      "top3_texts": [
        "我最近开始跑步，每天跑5公里。",
        "我换了个新手机，拍照效果不错。",
        "我这个月体重增加了5公斤，得减肥了。"
      ],
      "analysis": "⚠ 最佳匹配在第3位（非首位）"
    },
    {
      "id": "S8",
      "name": "情感推理（情绪原因）",
      "query": "我为什么心情不好",
      "passed": true,
      "top1_hit": false,
      "top3_hit": true,
      "top3_scores": [
        0.5,
        0.5,
        0.5
      ],
      "top3_texts": [
        "昨天晚上睡得很好。",
        "中午吃了红烧肉，味道还行。",
        "今天在会议室被老板批评了。"
      ],
      "analysis": "⚠ 最佳匹配在第3位（非首位）"
    },
    {
      "id": "S9",
      "name": "跨话题模糊指代",
      "query": "我之前说的那个计划",
      "passed": true,
      "top1_hit": false,
      "top3_hit": true,
      "top3_scores": [
        0.15000000000000002,
        0.15000000000000002,
        0.15000000000000002
      ],
      "top3_texts": [
        "Python 3.12 的新特性挺多的。",
        "今天的晚饭还不错。",
        "我想明年去日本旅游，看看樱花。"
      ],
      "analysis": "⚠ 最佳匹配在第3位（非首位）"
    },
    {
      "id": "S10",
      "name": "人称指代",
      "query": "他送我的东西好用吗",
      "passed": true,
      "top1_hit": false,
      "top3_hit": true,
      "top3_scores": [
        0.9,
        0.55,
        0.15000000000000002
      ],
      "top3_texts": [
        "李四说这个键盘不好用。",
        "张三送了我一把HHKB键盘。",
        "我自己买了一个鼠标。"
      ],
      "analysis": "⚠ 最佳匹配在第2位（非首位）"
    }
  ]
}